bicsgreeting/__init__.py
bicsgreeting/main.py
bicsgreeting-0.1.0.dist-info/entry_points.txt
bicsgreeting-0.1.0.dist-info/METADATA
bicsgreeting-0.1.0.dist-info/WHEEL
bicsgreeting-0.1.0.dist-info/RECORD
